{
    "culto": [
        {
            "titulo": "Culto de Missões", 
            "info": "Culto de Missões <br> ICE Betesda - 28/04/2024 ", 
            "img": "imagens/Fotos/tumb/igreja_viva_you.jpg",
            "link":"https://www.youtube.com/live/qenHcd4XLpQ?si=4RH-OwFEU-K_Y4ZJ"
        },
        {
            "titulo": "Culto de Celebração", 
            "info": "Sinais de uma igreja viva <br> Pr. Tiago - 21/04/2024 ", 
            "img": "imagens/Fotos/tumb/igreja_viva_you.jpg",
            "link":"https://www.youtube.com/live/qenHcd4XLpQ?si=6h26Ael3uiZg4TN-"
        }, 
        {
            "titulo": "Culto de Celebração", 
            "info": "Sinais de uma igreja viva <br> Pr. Gilvane - 14/04/2024 ", 
            "img": "imagens/Fotos/tumb/igreja_viva_you.jpg",
            "link":"https://www.youtube.com/live/K2bGb_DKbVM?si=n20W4a0Hb06EBS61"
        }
    ]
}
